Metadata-Version: 2.1
Name: traversal
Version: 1.0.1
Summary: Famous Matrix Traversals
Home-page: https://yoginth.gitlab.io
Author: Yoginth
Author-email: yoginth@zoho.com
License: UNKNOWN
Project-URL: Patreon, https://www.patreon.com/yoginth
Project-URL: Source, https://gitlab.com/yoginth/traversal
Platform: UNKNOWN
Classifier: Programming Language :: Python
Classifier: Natural Language :: English
Classifier: Environment :: Plugins
Classifier: Operating System :: OS Independent
Classifier: Intended Audience :: Developers
Classifier: License :: OSI Approved :: MIT License
